{
  "startYear": 2003,
  "startMonth": 5,
  "endYear": 2020,
  "endMonth": 7,
  "events": [
    {
      "topText": "свадьба",
      "bottomText": "2003 АПР",
      "eventLink": "wedding",
      "year": 2003,
      "month": 4,
      "settings": {
        "textColor": "",
        "hoverTextColor": "",
        "bgColor": "",
        "hoverBgColor": ""
      }
    },
    {
      "topText": "Аэротруба",
      "bottomText": "2017 ДЕК",
      "eventLink": "aerotruba",
      "year": 2017,
      "month": 12,
      "settings": {
        "textColor": "",
        "hoverTextColor": "",
        "bgColor": "",
        "hoverBgColor": ""
      }
    },
     {
      "topText": "Прыжочки",
      "bottomText": "2018 ОКТ",
      "eventLink": "prizki",
      "year": 2018,
      "month": 10,
      "settings": {
        "textColor": "",
        "hoverTextColor": "",
        "bgColor": "",
        "hoverBgColor": ""
      }
    },
    {
      "topText": "Золотое Кольцо",
      "bottomText": "2020 АВГ",
      "eventLink": "poezdki",
      "year": 2020,
      "month": 7,
      "settings": {
        "textColor": "",
        "hoverTextColor": "",
        "bgColor": "",
        "hoverBgColor": ""
      }
    }
  ]
}
