{
  "startYear": 2003,
  "startMonth": 5,
  "endYear": 2017,
  "endMonth": 12,
  "events": [
    {
      "topText": "свадьба",
      "bottomText": "2003 АПР",
      "eventLink": "wedding",
      "year": 2003,
      "month": 4,
      "settings": {
        "textColor": "",
        "hoverTextColor": "",
        "bgColor": "",
        "hoverBgColor": ""
      }
    },
    {
      "topText": "Аэротрубв",
      "bottomText": "2017 ДЕК",
      "eventLink": "aerotruba",
      "year": 2017,
      "month": 12,
      "settings": {
        "textColor": "",
        "hoverTextColor": "",
        "bgColor": "",
        "hoverBgColor": ""
      }
    }
  ]
}
